{"sections":{"1650891033bae15b05":{"type":"image-with-text","blocks":{"fd63bf46-7b83-450b-9205-e98d3bb15657":{"type":"background_shape","settings":{"shape":"shape_6","blob_type":7,"size":80,"opacity":100,"blur":0,"horizontal_position":79,"vertical_position":29,"rotate":-42,"enable_parallax":true,"parallax_speed":3,"color":"background","color_scheme":"secondary"}},"175e66d3-20ec-47c8-b628-6580300f4f5f":{"type":"sticker","disabled":true,"settings":{"shape":"pym_shape_8","color":"bg-scheme-accent-8 text-scheme-accent-8-overlay","sticker_multiply":false,"width":420,"horizontal_position":0,"vertical_position":48,"rotate":28,"sticker_opacity":1,"show_sticker_on_mobile":false,"show_sticker_on_desktop":true,"rotation_animation":"none","enable_parallax":true,"parallax_speed":1,"half_image_width_on_mobile":true}},"140e7989-8375-45bf-b75f-61897a50b73a":{"type":"sticker","settings":{"shape":"pym_shape_5","color":"bg-scheme-accent-16 text-scheme-accent-16-overlay","sticker_multiply":true,"width":150,"horizontal_position":3,"vertical_position":25,"rotate":58,"sticker_opacity":1,"show_sticker_on_mobile":false,"show_sticker_on_desktop":true,"rotation_animation":"none","enable_parallax":false,"parallax_speed":8,"half_image_width_on_mobile":true}},"44db3a15-912c-4e75-9108-ecf8cab92049":{"type":"sticker","settings":{"shape":"pym_shape_8","color":"bg-scheme-accent-4 text-scheme-accent-4-overlay","sticker_multiply":true,"width":130,"horizontal_position":7,"vertical_position":17,"rotate":-14,"sticker_opacity":1,"show_sticker_on_mobile":false,"show_sticker_on_desktop":true,"rotation_animation":"none","enable_parallax":false,"parallax_speed":3,"half_image_width_on_mobile":true}},"1fc86433-710f-4d70-8d4d-52eec3b81699":{"type":"sticker","settings":{"shape":"pym_shape_6","color":"bg-scheme-accent-8 text-scheme-accent-8-overlay","sticker_multiply":true,"width":300,"horizontal_position":52,"vertical_position":71,"rotate":34,"sticker_opacity":1,"show_sticker_on_mobile":false,"show_sticker_on_desktop":true,"rotation_animation":"none","enable_parallax":false,"parallax_speed":3,"half_image_width_on_mobile":true}},"33c720d7-5be3-4502-9ccf-850da10daa74":{"type":"sticker","settings":{"shape":"pym_shape_5","color":"bg-scheme-accent-4 text-scheme-accent-4-overlay","sticker_multiply":true,"width":120,"horizontal_position":47,"vertical_position":52,"rotate":-8,"sticker_opacity":1,"show_sticker_on_mobile":false,"show_sticker_on_desktop":true,"rotation_animation":"none","enable_parallax":false,"parallax_speed":3,"half_image_width_on_mobile":true}},"e05f0852-253f-4a1e-ba08-e1762ab32ad6":{"type":"sticker","settings":{"shape":"pym_shape_8","color":"bg-scheme-accent-16 text-scheme-accent-16-overlay","sticker_multiply":true,"width":300,"horizontal_position":98,"vertical_position":31,"rotate":-84,"sticker_opacity":1,"show_sticker_on_mobile":false,"show_sticker_on_desktop":true,"rotation_animation":"none","enable_parallax":true,"parallax_speed":3,"half_image_width_on_mobile":true}},"173f57b7-9359-45db-b3fe-1ed0cb09b26f":{"type":"sticker","disabled":true,"settings":{"shape":"pym_shape_6","color":"bg-scheme-accent-4 text-scheme-accent-4-overlay","sticker_multiply":true,"width":150,"horizontal_position":51,"vertical_position":23,"rotate":24,"sticker_opacity":1,"show_sticker_on_mobile":false,"show_sticker_on_desktop":true,"rotation_animation":"none","enable_parallax":false,"parallax_speed":3,"half_image_width_on_mobile":true}},"de3259cb-1604-4577-953d-101ab89a7bc1":{"type":"sticker","settings":{"shape":"pym_shape_5","color":"bg-scheme-accent-16 text-scheme-accent-16-overlay","sticker_multiply":false,"width":100,"horizontal_position":0,"vertical_position":17,"rotate":-32,"sticker_opacity":1,"show_sticker_on_mobile":true,"show_sticker_on_desktop":false,"rotation_animation":"none","enable_parallax":false,"parallax_speed":3,"half_image_width_on_mobile":true}},"05298369-2844-4997-bf32-4ac4ca32bcf7":{"type":"sticker","settings":{"shape":"pym_shape_6","color":"bg-scheme-accent-4 text-scheme-accent-4-overlay","sticker_multiply":true,"width":100,"horizontal_position":4,"vertical_position":27,"rotate":0,"sticker_opacity":1,"show_sticker_on_mobile":true,"show_sticker_on_desktop":false,"rotation_animation":"none","enable_parallax":false,"parallax_speed":3,"half_image_width_on_mobile":true}}},"block_order":["fd63bf46-7b83-450b-9205-e98d3bb15657","175e66d3-20ec-47c8-b628-6580300f4f5f","140e7989-8375-45bf-b75f-61897a50b73a","44db3a15-912c-4e75-9108-ecf8cab92049","1fc86433-710f-4d70-8d4d-52eec3b81699","33c720d7-5be3-4502-9ccf-850da10daa74","e05f0852-253f-4a1e-ba08-e1762ab32ad6","173f57b7-9359-45db-b3fe-1ed0cb09b26f","de3259cb-1604-4577-953d-101ab89a7bc1","05298369-2844-4997-bf32-4ac4ca32bcf7"],"settings":{"background-color":"","padding_top":0,"padding_bottom":10,"image":"shopify:\/\/shop_images\/hero5.png","crop":"","image_shape":"default","blob_type":2,"rotate_image":0,"image_position":"right","image_size":"three_fifths","disable_media_style":true,"text_alignment":"text-left","text_color":"#000000","title":"Mental wellness made simple.","heading_size":"heading-base","title_uppercase":false,"subtitle":"","subtitle_size":"heading-template","subtitle_uppercase":false,"subtitle_font":"font-accent","richtext":"<p>With science-supported nutrients for elevated moods and improved neurotransmitter function.<\/p>","button_link":"shopify:\/\/collections\/shop","button_label":"SHOP NOW"}},"165946104866676941":{"type":"image-with-text","blocks":{"5d86522d-41ed-4320-aba8-48eed9194cae":{"type":"shape_divider","settings":{"target_section":"below","target_section_color_scheme":"primary","style":"customshape_1919x170","flip_horizontal":true,"enable_animation":false,"animation_direction":""}},"63a2c446-f0a8-4004-afef-1e213b662d98":{"type":"shape_divider","settings":{"target_section":"above","target_section_color_scheme":"primary","style":"customshape_1919x170","flip_horizontal":true,"enable_animation":false,"animation_direction":""}}},"block_order":["5d86522d-41ed-4320-aba8-48eed9194cae","63a2c446-f0a8-4004-afef-1e213b662d98"],"settings":{"background-color":"#F1D09F","padding_top":30,"padding_bottom":25,"image":"shopify:\/\/shop_images\/hero1.png","crop":"","image_shape":"default","blob_type":1,"rotate_image":0,"image_position":"left","image_size":"half","disable_media_style":false,"text_alignment":"text-left","text_color":"#000000","title":"Discover your mental wellness solution","heading_size":"heading-base","title_uppercase":true,"subtitle":"","subtitle_size":"heading-template","subtitle_uppercase":false,"subtitle_font":"font-accent","richtext":"<p>Take the quiz created by Neuroscientists & Nutritional Psychiatrists to create your personal mental hygiene solution.<\/p>","button_link":"shopify:\/\/pages\/quiz","button_label":"Take the quiz"}},"1659460730a3258ded":{"type":"rich-text","settings":{"background-color":"#FFF7E8","padding_top":70,"padding_bottom":70,"text_align":"text-center","title":"We did the research, so you don’t have to.","heading_size":"heading-base","heading_font":"font-heading","rich_text":"<p>Our commitment to delivering accessible and effective products drives everything we do. You won't find any fillers or added sugar in our products. Only what your brain needs to thrive.<\/p>","text_size":"text-base","text_font":"font-main","content_width_desktop":"lg:w-full","button_link":"","button_label":"Shop Now"}},"16618935555573463a":{"type":"image-with-text","blocks":{"915eff51-8e19-419f-b89c-f92b5838b9b8":{"type":"sticker","settings":{"shape":"pym_shape_7","color":"bg-scheme-accent-16 text-scheme-accent-16-overlay","sticker_multiply":false,"width":400,"horizontal_position":3,"vertical_position":30,"rotate":-22,"sticker_opacity":1,"show_sticker_on_mobile":true,"show_sticker_on_desktop":true,"rotation_animation":"none","enable_parallax":false,"parallax_speed":3,"half_image_width_on_mobile":true}},"79d8d8f9-d7ec-4f3e-88b0-c5041cc7dd49":{"type":"sticker","settings":{"shape":"pym_shape_6","color":"bg-scheme-accent-5 text-scheme-accent-5-overlay","sticker_multiply":false,"width":900,"horizontal_position":61,"vertical_position":51,"rotate":-36,"sticker_opacity":1,"show_sticker_on_mobile":true,"show_sticker_on_desktop":true,"rotation_animation":"none","enable_parallax":false,"parallax_speed":3,"half_image_width_on_mobile":true}}},"block_order":["915eff51-8e19-419f-b89c-f92b5838b9b8","79d8d8f9-d7ec-4f3e-88b0-c5041cc7dd49"],"settings":{"background-color":"","padding_top":0,"padding_bottom":0,"image":"shopify:\/\/shop_images\/raghu_appasani.png","crop":"aspect-w-1 aspect-h-1","image_shape":"default","blob_type":1,"rotate_image":0,"image_position":"left","image_size":"half","disable_media_style":false,"text_alignment":"text-left","text_color":"#000000","title":"Dr. Raghu Appasani, MD","heading_size":"text-2xl","title_uppercase":true,"subtitle":"Psychiatrist & Neuroscientist","subtitle_size":"text-base","subtitle_uppercase":true,"subtitle_font":"font-accent","richtext":"<p>Dr. Raghu Appasani is an Integrative Psychiatrist, Neuroscientist, and Social Entrepreneur focused on bridging the gap between western and eastern practices to create a wholesome society by taking a proactive approach to health.<\/p>","button_link":"","button_label":"Shop Now"}},"1661893583eefefb74":{"type":"image-with-text","settings":{"background-color":"","padding_top":0,"padding_bottom":50,"image":"shopify:\/\/shop_images\/nicole_buerkins.png","crop":"aspect-w-1 aspect-h-1","image_shape":"default","blob_type":1,"rotate_image":0,"image_position":"right","image_size":"half","disable_media_style":false,"text_alignment":"text-left","text_color":"#000000","title":"Dr. Nicole Beurkens, PhD","heading_size":"text-2xl","title_uppercase":true,"subtitle":"Psychologist & Nutritionist","subtitle_size":"text-base","subtitle_uppercase":true,"subtitle_font":"font-accent","richtext":"<p>Dr. Nicole Beurkens is the world's leading holistic child psychologist. She has dedicated her 25 year career to providing parents with simple, effective, research-based strategies that get to the root of children's attention, anxiety, mood, and behavior challenges so they can reach their highest potential.<\/p>","button_link":"","button_label":"Shop Now"}},"1662492625bbae508f":{"type":"rich-text","blocks":{"a2d4253d-8205-4c76-9ffb-7bd4e98478da":{"type":"shape_divider","settings":{"target_section":"above","target_section_color_scheme":"primary","style":"customshape3_1919x130","flip_horizontal":true,"enable_animation":false,"animation_direction":""}},"73ea8ef9-36d0-4ea0-9e8c-d0aee0958269":{"type":"shape_divider","settings":{"target_section":"below","target_section_color_scheme":"primary","style":"customshape2_1919x120","flip_horizontal":true,"enable_animation":false,"animation_direction":""}}},"block_order":["a2d4253d-8205-4c76-9ffb-7bd4e98478da","73ea8ef9-36d0-4ea0-9e8c-d0aee0958269"],"settings":{"background-color":"#F1D09F","padding_top":50,"padding_bottom":80,"image":"shopify:\/\/shop_images\/Quotes.png","text_align":"text-center","title":"PYM's approach to dietary supplements is quite different compared to other brands","heading_size":"heading-base","heading_font":"font-heading","rich_text":"<p><a href=\"https:\/\/www.honestbrandreviews.com\/reviews\/pym-mood-chews-review\/\" target=\"_blank\" title=\"https:\/\/www.honestbrandreviews.com\/reviews\/pym-mood-chews-review\/\"><em>- Honest Brand Reviews<\/em><\/a><\/p>","text_size":"text-base","text_font":"font-main","content_width_desktop":"lg:w-full","button_link":"","button_label":""}},"1661819995fd348311":{"type":"featured-collection","settings":{"padding_top":50,"padding_bottom":70,"title":"Simplify Your Mental Wellness Routine","subheading":"Research-backed nutrients to boost neurotransmitters like serotonin, dopamine and oxytocin while improving long-term brain health.","collection":"shop","no_products":6,"show_view_all":false,"enable_quick_buy":true,"display_on_card":false,"layout":"grid","products_per_row_mobile":"1","products_per_row_desktop":3,"slideshow_focus":"center","mobile_slide_width":"three_fifths","desktop_slide_width":40,"autoscroll_mode":"1","product_tiles_aspect_ratio":"aspect-w-1 aspect-h-1","image_shape":"default","color_scheme":"primary","use_gradient_background":false}},"1662990776429ceabb":{"type":"rich-text","blocks":{"18148895-1f86-49db-8ba5-17379c90f72f":{"type":"shape_divider","settings":{"target_section":"above","target_section_color_scheme":"primary","style":"customshape3_1919x130","flip_horizontal":false,"enable_animation":false,"animation_direction":""}},"5f41875e-82d0-4fb8-99ee-21891d658157":{"type":"shape_divider","settings":{"target_section":"below","target_section_color_scheme":"primary","style":"customshape_1919x170","flip_horizontal":false,"enable_animation":false,"animation_direction":""}}},"block_order":["18148895-1f86-49db-8ba5-17379c90f72f","5f41875e-82d0-4fb8-99ee-21891d658157"],"settings":{"background-color":"#F1D09F","padding_top":70,"padding_bottom":70,"image":"shopify:\/\/shop_images\/stars.png","text_align":"text-center","title":"“The PYM formula provides a great combo of ingredients at the right dose, and in a form that's easy to take. I notice a difference on the days I take them, and recommend them for anyone looking to support themselves in a natural and effective way.\"","heading_size":"text-lg","heading_font":"font-heading","rich_text":"<p><strong>- DR. NICOLE BEURKENS<br\/><\/strong>PSYCHOLOGIST & NUTRITIONIST<\/p>","text_size":"text-base","text_font":"font-main","content_width_desktop":"lg:w-2\/3","button_link":"","button_label":"Shop Now"}},"165089168609b8f684":{"type":"blog-posts","settings":{"padding_top":70,"padding_bottom":70,"title":"LEARN","blog":"learn","post_limit":3,"crop":"aspect-w-1 aspect-h-1","image_shape":"default","blog_show_author":false,"blog_show_date":false,"show_post_excerpt":false,"show_view_all":true,"color_scheme":"primary","use_gradient_background":false}},"1663011143b5bd53de":{"type":"image-with-text","blocks":{"982eec6a-b240-4055-8923-347f1cb8ebc1":{"type":"shape_divider","settings":{"target_section":"above","target_section_color_scheme":"primary","style":"customshape_1919x170","flip_horizontal":false,"enable_animation":false,"animation_direction":""}},"9a3f9222-ab32-4b57-a4f5-cff19f99e2a6":{"type":"sticker","settings":{"shape":"pym_shape_1","color":"bg-scheme-accent text-scheme-accent-overlay","sticker_multiply":false,"width":150,"horizontal_position":88,"vertical_position":21,"rotate":0,"sticker_opacity":1,"show_sticker_on_mobile":false,"show_sticker_on_desktop":true,"rotation_animation":"none","enable_parallax":false,"parallax_speed":3,"image":"shopify:\/\/shop_images\/PYM_Brand-Mark_Black.png","half_image_width_on_mobile":true}}},"block_order":["982eec6a-b240-4055-8923-347f1cb8ebc1","9a3f9222-ab32-4b57-a4f5-cff19f99e2a6"],"settings":{"background-color":"#F1D09F","padding_top":70,"padding_bottom":25,"image":"shopify:\/\/shop_images\/6gsTr4zTWZd4FaAiyTSUFUk0yJnTJX6R0ej9N7z5.png","crop":"aspect-w-3 aspect-h-4","image_shape":"default","blob_type":1,"rotate_image":0,"image_position":"left","image_size":"half","disable_media_style":false,"text_alignment":"text-left","text_color":"#000000","title":"Meet PYM","heading_size":"text-2xl","title_uppercase":true,"subtitle":"","subtitle_size":"heading-template","subtitle_uppercase":false,"subtitle_font":"font-accent","richtext":"<p>PYM discovered that people were only prioritizing their mental health when they had severe symptoms. We need people to prioritize their mental health on a daily basis and want to make the idea of taking care of your mental health as easy and important  as consistently brushing your  teeth. With that in mind, we hope you will join our mission for  mental hygiene- daily rituals relating to mental wellbeing that enable us to prioritize our minds’ healthy and optimal functioning every single day. No more fake moods, no more waking up on the wrong side of the bed, time for a consistent foundation for a strong, resilient and healthy mind. A better life starts with better days.<\/p>","button_link":"shopify:\/\/pages\/our-story","button_label":"Our Story"}},"166301115056dcaf4d":{"type":"image-with-text","blocks":{"5345bb0e-59a6-424e-abe0-5a4ff79c1a15":{"type":"shape_divider","settings":{"target_section":"below","target_section_color_scheme":"primary","style":"customshape_1919x170","flip_horizontal":false,"enable_animation":false,"animation_direction":""}}},"block_order":["5345bb0e-59a6-424e-abe0-5a4ff79c1a15"],"settings":{"background-color":"#F1D09F","padding_top":30,"padding_bottom":0,"image":"shopify:\/\/shop_images\/Hand3.png","crop":"aspect-w-1 aspect-h-1","image_shape":"default","blob_type":1,"rotate_image":0,"image_position":"right","image_size":"half","disable_media_style":false,"text_alignment":"text-right","text_color":"#000000","title":"Your Purchase of PYM Matters","heading_size":"text-xl","title_uppercase":false,"subtitle":"PYM donates 1% of its sales to Bring Change to Mind, a mental health nonprofit working to end the stigma and discrimination surrounding mental illness.","subtitle_size":"text-base","subtitle_uppercase":false,"subtitle_font":"font-main","richtext":"","button_link":"","button_label":"Shop Now"}},"e6955944-4b2b-42de-aeed-36bd3ad4b16b":{"type":"rich-text","settings":{"background-color":"#FFF7E8","padding_top":40,"padding_bottom":0,"text_align":"text-center","title":"Prepare Your Mind with our community.","heading_size":"heading-base","heading_font":"font-heading","rich_text":"<p>Get daily mental hygiene tips and laugh about the anxious thoughts we all share!<\/p>","text_size":"text-base","text_font":"font-main","content_width_desktop":"lg:w-2\/3","button_link":"","button_label":""}},"16630176002145e018":{"type":"apps","blocks":{"5dd7a06b-6bb2-4dab-9b38-519fbae48a2f":{"type":"shopify:\/\/apps\/maestrooo-section-feed\/blocks\/app-block\/43cd482b-515a-4e82-b170-05d391763cd2","settings":{"title":"","subheading":"","button_text":"","button_link":"","layout":"grid","image_size":"large","add_spacing":true,"rows_count":1,"show_author":false,"show_caption":true,"show_date":true,"click_action":"open_instagram","heading_color":"#000000","subheading_color":"#000000","button_background":"#000000","button_color":"#ffffff","overlay_color":"#000000","overlay_text_color":"#ffffff","overlay_opacity":65}}},"block_order":["5dd7a06b-6bb2-4dab-9b38-519fbae48a2f"],"settings":{}},"16630176242001ee28":{"type":"rich-text","blocks":{"654f5e82-2882-417a-b2c1-4357c176bdf8":{"type":"shape_divider","settings":{"target_section":"above","target_section_color_scheme":"primary","style":"customshape2_1919x120","flip_horizontal":false,"enable_animation":false,"animation_direction":""}}},"block_order":["654f5e82-2882-417a-b2c1-4357c176bdf8"],"settings":{"background-color":"#F1D09F","padding_top":25,"padding_bottom":0,"text_align":"text-center","title":"","heading_size":"heading-base","heading_font":"font-heading","rich_text":"","text_size":"text-base","text_font":"font-main","content_width_desktop":"lg:w-2\/3","button_link":"","button_label":"Shop Now"}}},"order":["1650891033bae15b05","165946104866676941","1659460730a3258ded","16618935555573463a","1661893583eefefb74","1662492625bbae508f","1661819995fd348311","1662990776429ceabb","165089168609b8f684","1663011143b5bd53de","166301115056dcaf4d","e6955944-4b2b-42de-aeed-36bd3ad4b16b","16630176002145e018","16630176242001ee28"]}